hadiuka/__init__.py
hadiuka/__main__.py
hadiuka/config.py
hadiuka/converter.py
hadiuka/mapping.json
hadiuka/runner.py
hadiuka/translator.py
hadiuka-0.0.3.dist-info/METADATA
hadiuka-0.0.3.dist-info/WHEEL
hadiuka-0.0.3.dist-info/entry_points.txt
hadiuka-0.0.3.dist-info/top_level.txt
hadiuka-0.0.3.dist-info/RECORD
