Metadata-Version: 2.1
Name: hadiuka
Version: 0.0.3
Summary: Python in Ukrainian
Author: Sóla Lusøt
Requires-Dist: pwcp<0.11,>=0.10
Provides-Extra: tests
Requires-Dist: pytest; extra == "tests"
